README.md
setup.cfg
setup.py
PySlovnik/__init__.py
PySlovnik/__main__.py
pyslovnik.egg-info/PKG-INFO
pyslovnik.egg-info/SOURCES.txt
pyslovnik.egg-info/dependency_links.txt
pyslovnik.egg-info/requires.txt
pyslovnik.egg-info/top_level.txt