Metadata-Version: 1.1
Name: pyslovnik
Version: 0.1
Summary: Python wrapper pro Internetovou jazykovou příručku od Ústavu pro jazyk český Akademie věd České republiky
Home-page: http://github.com/CrumblyLiquid/PySlovnik
Author: CrumblyLiquid
Author-email: crumblyliquid@gmail.com
License: GNU GPLv3
Download-URL: https://github.com/CrumblyLiquid/PySlovnik/archive/refs/tags/0.1.tar.gz
Keywords: czech,dictionary
Platform: UNKNOWN
